LICENSE.txt
MANIFEST.in
README.rst
setup.py
pyborgeous/__init__.py
pyborgeous/codestrings.py
pyborgeous/docstrings.py
pyborgeous/pyborgeous.py
pyborgeous.egg-info/PKG-INFO
pyborgeous.egg-info/SOURCES.txt
pyborgeous.egg-info/dependency_links.txt
pyborgeous.egg-info/entry_points.txt
pyborgeous.egg-info/requires.txt
pyborgeous.egg-info/top_level.txt
pyborgeous.egg-info/zip-safe