Metadata-Version: 1.1
Name: pyborgeous
Version: 0.5.0
Summary: Pyborgeous is an implementation of Jorge Luis Borges' Library of Babel
Home-page: https://github.com/Spacehug/pyborgeous
Author: Spacehug
Author-email: spacehug.o0@gmail.com
License: MIT
Keywords: Gorge Luis Borges Library of Babel unicode
Platform: UNKNOWN
Classifier: Development Status :: 3 - Alpha
Classifier: Intended Audience :: Science/Research
Classifier: Topic :: Scientific/Engineering :: Information Analysis
Classifier: License :: OSI Approved :: MIT License
Classifier: Programming Language :: Python :: 3.6
Classifier: Programming Language :: Python :: 3.6.1
